sun_phy/__init__.py
sun_phy/mr_fsk/__init__.py
sun_phy/mr_fsk/mr_fsk.py
sun_phy/mr_fsk/mr_fsk_modulator.py
sun_phy/mr_o_qpsk/__init__.py
sun_phy/mr_o_qpsk/mr_o_qpsk_modulator.py
sun_phy/mr_ofdm/__init__.py
sun_phy/mr_ofdm/fields.py
sun_phy/mr_ofdm/modulations.py
sun_phy/mr_ofdm/mr_ofdm_modulator.py
sun_phy/mr_ofdm/ofdm_modulator.py
sun_phy/mr_ofdm/pn9.py
sun_phy/mr_ofdm/rate_encoder.py
sun_phy/tests/__init__.py
sun_phy/tests/test_802_15_4g_L.py
sun_phy/tests/test_802_15_4g_M.py
sun_phy/tests/test_802_15_4g_N.py
sun_phy/tests/test_802_15_4g_O.py
sun_phy/tests/test_general.py
sun_phy/tests/test_mr_fsk.py
sun_phy/tests/test_mr_o_qpsk.py
sun_phy/tests/test_mr_ofdm.py
sun_phy/tests/tests_tools.py
sun_phy/tools/__init__.py
sun_phy/tools/bits.py
sun_phy/tools/errors.py
sun_phy/tools/fixedpoint.py
sun_phy/tools/modulations.py
sun_phy/tools/operations.py
sun_phy/tools/pn9.py
sun_phy-0.1.0.dist-info/LICENSE
sun_phy-0.1.0.dist-info/METADATA
sun_phy-0.1.0.dist-info/WHEEL
sun_phy-0.1.0.dist-info/top_level.txt
sun_phy-0.1.0.dist-info/RECORD
