Metadata-Version: 2.1
Name: sun-phy
Version: 0.1.0
Summary: Software SUN PHY modulator
Author: Sebastien Deriaz
Author-email: sebastien.deriaz1@gmail.com
Keywords: python,802.15.4g,mr-fsk,mr-o-qpsk,mr-ofdm,ofdm,modulation,modulator,sdr,iq
Classifier: Development Status :: 3 - Alpha
Classifier: Intended Audience :: Education
Classifier: Programming Language :: Python :: 3
Classifier: Operating System :: Unix
Classifier: Operating System :: MacOS :: MacOS X
Classifier: Operating System :: Microsoft :: Windows
License-File: LICENSE
Requires-Dist: numpy
Requires-Dist: colorama
